wdbo_algo/__init__.py
wdbo_algo/model.py
wdbo_algo/optimizer.py
wdbo_algo-1.0.7.dist-info/LICENCE
wdbo_algo-1.0.7.dist-info/METADATA
wdbo_algo-1.0.7.dist-info/WHEEL
wdbo_algo-1.0.7.dist-info/top_level.txt
wdbo_algo-1.0.7.dist-info/RECORD
