Metadata-Version: 2.1
Name: wdbo_algo
Version: 1.0.7
Summary: W-DBO Algotithm for Dynamic Bayesian Optimization
Author-email: Anthony Bardou <anthony.bardou@epfl.ch>
Project-URL: Project, https://github.com/WDBO-ALGORITHM
Classifier: Programming Language :: Python :: 3
Requires-Python: >=3.8
License-File: LICENCE
Requires-Dist: wdbo-criterion
Requires-Dist: gpytorch
Requires-Dist: torch
Requires-Dist: botorch
